lotecc/__init__.py
lotecc/cli.py
lotecc/lotecc.py
lotecc-0.1.1.dist-info/AUTHORS.rst
lotecc-0.1.1.dist-info/LICENSE
lotecc-0.1.1.dist-info/METADATA
lotecc-0.1.1.dist-info/WHEEL
lotecc-0.1.1.dist-info/entry_points.txt
lotecc-0.1.1.dist-info/top_level.txt
lotecc-0.1.1.dist-info/RECORD
