Metadata-Version: 2.1
Name: lotecc
Version: 0.1.1
Summary: Convert files between Simplified Chinese and Traditional Chinese.
Home-page: https://github.com/lonsty/lotecc
Author: Allen Shaw
Author-email: lonsty@sina.com
License: MIT license
Keywords: lotecc
Platform: UNKNOWN
Classifier: Development Status :: 2 - Pre-Alpha
Classifier: Intended Audience :: Developers
Classifier: License :: OSI Approved :: MIT License
Classifier: Natural Language :: English
Classifier: Programming Language :: Python :: 3
Classifier: Programming Language :: Python :: 3.6
Classifier: Programming Language :: Python :: 3.7
Classifier: Programming Language :: Python :: 3.8
Requires-Python: >=3.6
Requires-Dist: Click (>=7.0)
Requires-Dist: pydantic (>=1.5.1)
Requires-Dist: opencc-python-reimplemented (>=0.1.5)
